Metadata-Version: 1.0
Name: distributions-shivani-781
Version: 1.3
Summary: Gaussian & Normal distributions
Home-page: UNKNOWN
Author: Shivani Chauhan
Author-email: UNKNOWN
License: UNKNOWN
Platform: UNKNOWN
